mitsuba_scene_description/__init__.py
mitsuba_scene_description/bsdfs.py
mitsuba_scene_description/emitters.py
mitsuba_scene_description/films.py
mitsuba_scene_description/integrators.py
mitsuba_scene_description/media.py
mitsuba_scene_description/phase.py
mitsuba_scene_description/py.typed
mitsuba_scene_description/rfilters.py
mitsuba_scene_description/samplers.py
mitsuba_scene_description/scene.py
mitsuba_scene_description/sensors.py
mitsuba_scene_description/shapes.py
mitsuba_scene_description/spectra.py
mitsuba_scene_description/textures.py
mitsuba_scene_description/utils.py
mitsuba_scene_description/volumes.py
mitsuba_scene_description-0.1.0.dist-info/METADATA
mitsuba_scene_description-0.1.0.dist-info/WHEEL
mitsuba_scene_description-0.1.0.dist-info/RECORD
