Metadata-Version: 2.4
Name: mitsuba-scene-description
Version: 0.1.0
Summary: Generated, typed, autocompletable Python API for composing Mitsuba scenes.
Project-URL: Homepage, https://github.com/pixelsandpointers/mitsuba-scene-description
Project-URL: Issues, https://github.com/pixelsandpointers/mitsuba-scene-description/issues
Author: Benjamin Beilharz
License: MIT
Classifier: License :: OSI Approved :: MIT License
Classifier: Programming Language :: Python :: 3
Classifier: Typing :: Typed
Requires-Python: >=3.9
